batch_mailchimp/__init__.py
batch_mailchimp/batches_api.py
batch_mailchimp/collections.py
batch_mailchimp/decorators.py
batch_mailchimp-1.2.2.dist-info/LICENSE
batch_mailchimp-1.2.2.dist-info/METADATA
batch_mailchimp-1.2.2.dist-info/WHEEL
batch_mailchimp-1.2.2.dist-info/top_level.txt
batch_mailchimp-1.2.2.dist-info/RECORD
