Metadata-Version: 2.1
Name: batch-mailchimp
Version: 1.2.2
Summary: A python client for MailChimp Marketing API, with batch support
Home-page: https://github.com/FullFact/python-batchmailchimp
Author: Andy Lulham
Author-email: andy.lulham@fullfact.org
License: MIT
Keywords: mailchimp marketing api client wrapper
Classifier: Development Status :: 5 - Production/Stable
Classifier: Intended Audience :: Developers
Classifier: Topic :: Software Development :: Libraries :: Python Modules
Classifier: License :: OSI Approved :: MIT License
Classifier: Programming Language :: Python :: 3
Classifier: Programming Language :: Python :: 3.8
Classifier: Programming Language :: Python :: 3.9
Classifier: Programming Language :: Python :: 3.10
License-File: LICENSE
Requires-Dist: mailchimp-marketing (>=3.0.80)
